ab_service/bff/__init__.py
ab_service/bff/main.py
ab_service/bff/routes/__init__.py
ab_service/bff/routes/identity_context.py
ab_bff_service-0.2.0.dist-info/METADATA
ab_bff_service-0.2.0.dist-info/WHEEL
ab_bff_service-0.2.0.dist-info/licenses/LICENSE
ab_bff_service-0.2.0.dist-info/RECORD
