Metadata-Version: 2.4
Name: ab-bff-service
Version: 0.2.0
Summary: Auth Broker BFF Service.
Author-email: Matthew Coulter <53892067+mattcoulter7@users.noreply.github.com>
License-File: LICENSE
Requires-Python: <4,>=3.12
Requires-Dist: ab-alembic-auto-migrate<1,>=0.2.0
Requires-Dist: ab-client-auth-client>=0.1.0
Requires-Dist: ab-client-token-validator>=0.1.0
Requires-Dist: ab-client-user>=0.1.0
Requires-Dist: ab-database[postgres-async,postgres-sync,sqlite-async]<1,>=0.2.2
Requires-Dist: ab-identity-context[fastapi]>=0.1.1
Requires-Dist: ab-logging>=0.1.2
Requires-Dist: fastapi<0.116,>=0.115.14
Requires-Dist: pydantic[email]<3,>=2.11.7
Requires-Dist: uvicorn<0.36,>=0.35.0
